milieudefensie/beslisboom.py
milieudefensie/grafieken.py
milieudefensie/model_non_linear_y.py
milieudefensie-0.0.3.dist-info/licenses/LICENSE
milieudefensie-0.0.3.dist-info/METADATA
milieudefensie-0.0.3.dist-info/WHEEL
milieudefensie-0.0.3.dist-info/top_level.txt
milieudefensie-0.0.3.dist-info/RECORD
