Metadata-Version: 2.4
Name: milieudefensie
Version: 0.0.3
Summary: Machine learning tools for environmental analysis
Author-email: Data team <data@milieudefensie.nl>
Project-URL: Homepage, https://milieudefensie.nl
Requires-Python: >=3.9
License-File: LICENSE
Requires-Dist: numpy<3.0.0,>=2.0.0
Requires-Dist: pandas<3.0.0,>=2.0.0
Requires-Dist: scikit-learn<2.0.0,>=1.0.0
Requires-Dist: matplotlib>=3.0.0
Requires-Dist: plotly>=6.0.0
Requires-Dist: shap>=0.40.0
Requires-Dist: xgboost>=3.0.0
Requires-Dist: lightgbm>=4.0.0
Requires-Dist: catboost>=1.0.0
Requires-Dist: tqdm>=4.0.0
Requires-Dist: requests>=2.0.0
Requires-Dist: seaborn>=0.13.2
Dynamic: license-file
